pdfcomments/__init__.py
pdfcomments/__main__.py
pdfcomments/py.typed
pdfcomments-0.1.dist-info/DESCRIPTION.rst
pdfcomments-0.1.dist-info/METADATA
pdfcomments-0.1.dist-info/RECORD
pdfcomments-0.1.dist-info/WHEEL
pdfcomments-0.1.dist-info/entry_points.txt
pdfcomments-0.1.dist-info/metadata.json
pdfcomments-0.1.dist-info/top_level.txt
