Metadata-Version: 2.0
Name: pdfcomments
Version: 0.1
Summary: extract comments from PDF
Home-page: UNKNOWN
Author: Michael Hoffman
Author-email: michael.hoffman@utoronto.ca
License: GPLv3
Platform: UNKNOWN
Requires-Python: >=3.6
Requires-Dist: PyPDF2
